<?xml version="1.0" encoding="utf-8" ?>
<NEKTAR>
    <GEOMETRY DIM="2" SPACE="2">
        <VERTEX>
            <V ID="0">   0.000000000000000    0.000000000000000    0.000000000000000 </V>
            <V ID="1">   1.000000000000000    0.000000000000000    0.000000000000000 </V>
            <V ID="2">   1.000000000000000    1.000000000000000    0.000000000000000 </V>
            <V ID="3">   0.000000000000000    1.000000000000000    0.000000000000000 </V>
            <V ID="4">   0.083333333333133    0.000000000000000    0.000000000000000 </V>
            <V ID="5">   0.166666666666267    0.000000000000000    0.000000000000000 </V>
            <V ID="6">   0.249999999999400    0.000000000000000    0.000000000000000 </V>
            <V ID="7">   0.333333333332607    0.000000000000000    0.000000000000000 </V>
            <V ID="8">   0.416666666665814    0.000000000000000    0.000000000000000 </V>
            <V ID="9">   0.499999999999022    0.000000000000000    0.000000000000000 </V>
            <V ID="10">   0.583333333332460    0.000000000000000    0.000000000000000 </V>
            <V ID="11">   0.666666666665899    0.000000000000000    0.000000000000000 </V>
            <V ID="12">   0.749999999999337    0.000000000000000    0.000000000000000 </V>
            <V ID="13">   0.833333333332892    0.000000000000000    0.000000000000000 </V>
            <V ID="14">   0.916666666666446    0.000000000000000    0.000000000000000 </V>
            <V ID="15">   1.000000000000000    0.083333333333133    0.000000000000000 </V>
            <V ID="16">   1.000000000000000    0.166666666666267    0.000000000000000 </V>
            <V ID="17">   1.000000000000000    0.249999999999400    0.000000000000000 </V>
            <V ID="18">   1.000000000000000    0.333333333332607    0.000000000000000 </V>
            <V ID="19">   1.000000000000000    0.416666666665814    0.000000000000000 </V>
            <V ID="20">   1.000000000000000    0.499999999999022    0.000000000000000 </V>
            <V ID="21">   1.000000000000000    0.583333333332460    0.000000000000000 </V>
            <V ID="22">   1.000000000000000    0.666666666665899    0.000000000000000 </V>
            <V ID="23">   1.000000000000000    0.749999999999337    0.000000000000000 </V>
            <V ID="24">   1.000000000000000    0.833333333332892    0.000000000000000 </V>
            <V ID="25">   1.000000000000000    0.916666666666446    0.000000000000000 </V>
            <V ID="26">   0.916666666666782    1.000000000000000    0.000000000000000 </V>
            <V ID="27">   0.833333333333565    1.000000000000000    0.000000000000000 </V>
            <V ID="28">   0.750000000000347    1.000000000000000    0.000000000000000 </V>
            <V ID="29">   0.666666666667361    1.000000000000000    0.000000000000000 </V>
            <V ID="30">   0.583333333334374    1.000000000000000    0.000000000000000 </V>
            <V ID="31">   0.500000000001388    1.000000000000000    0.000000000000000 </V>
            <V ID="32">   0.416666666667939    1.000000000000000    0.000000000000000 </V>
            <V ID="33">   0.333333333334490    1.000000000000000    0.000000000000000 </V>
            <V ID="34">   0.250000000001041    1.000000000000000    0.000000000000000 </V>
            <V ID="35">   0.166666666667361    1.000000000000000    0.000000000000000 </V>
            <V ID="36">   0.083333333333680    1.000000000000000    0.000000000000000 </V>
            <V ID="37">   0.000000000000000    0.916666666666782    0.000000000000000 </V>
            <V ID="38">   0.000000000000000    0.833333333333565    0.000000000000000 </V>
            <V ID="39">   0.000000000000000    0.750000000000347    0.000000000000000 </V>
            <V ID="40">   0.000000000000000    0.666666666667361    0.000000000000000 </V>
            <V ID="41">   0.000000000000000    0.583333333334374    0.000000000000000 </V>
            <V ID="42">   0.000000000000000    0.500000000001388    0.000000000000000 </V>
            <V ID="43">   0.000000000000000    0.416666666667939    0.000000000000000 </V>
            <V ID="44">   0.000000000000000    0.333333333334490    0.000000000000000 </V>
            <V ID="45">   0.000000000000000    0.250000000001041    0.000000000000000 </V>
            <V ID="46">   0.000000000000000    0.166666666667361    0.000000000000000 </V>
            <V ID="47">   0.000000000000000    0.083333333333680    0.000000000000000 </V>
            <V ID="48">   0.592979489637831    0.551123355926941    0.000000000000000 </V>
            <V ID="49">   0.325754520541114    0.390843797932483    0.000000000000000 </V>
            <V ID="50">   0.633131756368410    0.244324011994687    0.000000000000000 </V>
            <V ID="51">   0.690766244626997    0.658707662956147    0.000000000000000 </V>
            <V ID="52">   0.348450459781228    0.716851148057834    0.000000000000000 </V>
            <V ID="53">   0.775380553144225    0.902543075549911    0.000000000000000 </V>
            <V ID="54">   0.254725936615248    0.143162822126533    0.000000000000000 </V>
            <V ID="55">   0.856387293729684    0.249148585090229    0.000000000000000 </V>
            <V ID="56">   0.183566320983301    0.846953036035743    0.000000000000000 </V>
            <V ID="57">   0.873847169353863    0.928673097887054    0.000000000000000 </V>
            <V ID="58">   0.179705151345808    0.131830208597118    0.000000000000000 </V>
            <V ID="59">   0.868896041870960    0.143321757584768    0.000000000000000 </V>
            <V ID="60">   0.112003119140791    0.907665229595829    0.000000000000000 </V>
            <V ID="61">   0.055688035198142    0.885819780590688    0.000000000000000 </V>
            <V ID="62">   0.791683275228884    0.308300526488652    0.000000000000000 </V>
            <V ID="63">   0.380139277148913    0.193159714018361    0.000000000000000 </V>
            <V ID="64">   0.520549585370041    0.706259601646627    0.000000000000000 </V>
            <V ID="65">   0.795404160020497    0.486809606169253    0.000000000000000 </V>
            <V ID="66">   0.612761137478919    0.836403037724326    0.000000000000000 </V>
            <V ID="67">   0.466488118481533    0.289122534676008    0.000000000000000 </V>
            <V ID="68">   0.443789165587112    0.588471221385514    0.000000000000000 </V>
            <V ID="69">   0.454468974295689    0.837305595626184    0.000000000000000 </V>
            <V ID="70">   0.308410496094442    0.537096398402898    0.000000000000000 </V>
            <V ID="71">   0.458599800676917    0.452149762167128    0.000000000000000 </V>
            <V ID="72">   0.156358439634906    0.658708597400206    0.000000000000000 </V>
            <V ID="73">   0.915329106033805    0.797583540963137    0.000000000000000 </V>
            <V ID="74">   0.081495019434859    0.260615689184703    0.000000000000000 </V>
            <V ID="75">   0.733211076103312    0.070370132259117    0.000000000000000 </V>
            <V ID="76">   0.156280433673805    0.409792425400667    0.000000000000000 </V>
            <V ID="77">   0.630691981946231    0.368991268453653    0.000000000000000 </V>
            <V ID="78">   0.867699871852597    0.646036644870365    0.000000000000000 </V>
            <V ID="79">   0.554248133643478    0.141309862638009    0.000000000000000 </V>
            <V ID="80">   0.249391335978870    0.910063297083345    0.000000000000000 </V>
            <V ID="81">   0.647397491079845    0.585395334073542    0.000000000000000 </V>
            <V ID="82">   0.264113330732936    0.266804281420823    0.000000000000000 </V>
            <V ID="83">   0.707462266521858    0.230145334496952    0.000000000000000 </V>
            <V ID="84">   0.934280859055760    0.373162105576759    0.000000000000000 </V>
            <V ID="85">   0.377062110215599    0.061479999368791    0.000000000000000 </V>
            <V ID="86">   0.776902187932216    0.798973012315620    0.000000000000000 </V>
            <V ID="87">   0.930061524840265    0.880382992610176    0.000000000000000 </V>
            <V ID="88">   0.859042673206291    0.062438485825442    0.000000000000000 </V>
            <V ID="89">   0.087674399794831    0.127049069108505    0.000000000000000 </V>
            <V ID="90">   0.175776489566364    0.940367515680576    0.000000000000000 </V>
            <V ID="91">   0.894709508146697    0.499570525732565    0.000000000000000 </V>
            <V ID="92">   0.153775614970342    0.554585198625988    0.000000000000000 </V>
            <V ID="93">   0.869245469756035    0.422685755031211    0.000000000000000 </V>
            <V ID="94">   0.260236506940289    0.678211409048648    0.000000000000000 </V>
            <V ID="95">   0.364663293453493    0.266637119005937    0.000000000000000 </V>
            <V ID="96">   0.464572791830377    0.079045574256999    0.000000000000000 </V>
            <V ID="97">   0.553237820576387    0.915824399700317    0.000000000000000 </V>
            <V ID="98">   0.640737214800056    0.087892883352140    0.000000000000000 </V>
            <V ID="99">   0.229395733525700    0.488610932499588    0.000000000000000 </V>
            <V ID="100">   0.211207946151533    0.333443772441924    0.000000000000000 </V>
            <V ID="101">   0.441375765874056    0.712743655009654    0.000000000000000 </V>
            <V ID="102">   0.647875574528159    0.179212249858318    0.000000000000000 </V>
            <V ID="103">   0.241404456957181    0.586997983799792    0.000000000000000 </V>
            <V ID="104">   0.538892352352574    0.411562502822681    0.000000000000000 </V>
            <V ID="105">   0.922733346210196    0.575568333464171    0.000000000000000 </V>
            <V ID="106">   0.703360333254586    0.445440125953518    0.000000000000000 </V>
            <V ID="107">   0.204165977940849    0.755822622963151    0.000000000000000 </V>
            <V ID="108">   0.320857324470434    0.622812343248508    0.000000000000000 </V>
            <V ID="109">   0.508420115798827    0.213076802294431    0.000000000000000 </V>
            <V ID="110">   0.257829648264328    0.403659099344137    0.000000000000000 </V>
            <V ID="111">   0.384071041771806    0.343710963441747    0.000000000000000 </V>
            <V ID="112">   0.451628141073670    0.162834830727868    0.000000000000000 </V>
            <V ID="113">   0.544621486192878    0.337070458035187    0.000000000000000 </V>
            <V ID="114">   0.837018021952412    0.567772257506877    0.000000000000000 </V>
            <V ID="115">   0.489310096840335    0.773893781573721    0.000000000000000 </V>
            <V ID="116">   0.773998242897328    0.632624617226181    0.000000000000000 </V>
            <V ID="117">   0.609482285929514    0.463667454476105    0.000000000000000 </V>
            <V ID="118">   0.676758321672940    0.296237966172428    0.000000000000000 </V>
            <V ID="119">   0.412341271453952    0.783923308492761    0.000000000000000 </V>
            <V ID="120">   0.787559566934737    0.386892298499219    0.000000000000000 </V>
            <V ID="121">   0.382792147496256    0.493125804042485    0.000000000000000 </V>
            <V ID="122">   0.113709836941135    0.328977338600833    0.000000000000000 </V>
            <V ID="123">   0.814887527690771    0.716259709770493    0.000000000000000 </V>
            <V ID="124">   0.521171627410082    0.841720704105024    0.000000000000000 </V>
            <V ID="125">   0.650970615991678    0.748218340214125    0.000000000000000 </V>
            <V ID="126">   0.403247548521741    0.640889411789118    0.000000000000000 </V>
            <V ID="127">   0.463785616834152    0.375849994611243    0.000000000000000 </V>
            <V ID="128">   0.219462203491388    0.203786645769598    0.000000000000000 </V>
            <V ID="129">   0.724492524541718    0.345088570002280    0.000000000000000 </V>
            <V ID="130">   0.108720454520290    0.745515546541241    0.000000000000000 </V>
            <V ID="131">   0.720069320542856    0.554023433596364    0.000000000000000 </V>
            <V ID="132">   0.564747242659887    0.759212676539925    0.000000000000000 </V>
            <V ID="133">   0.176395546701251    0.261451662699166    0.000000000000000 </V>
            <V ID="134">   0.344416968512725    0.790553477722213    0.000000000000000 </V>
            <V ID="135">   0.448454898285615    0.916002629534090    0.000000000000000 </V>
            <V ID="136">   0.529178191939558    0.494787760849760    0.000000000000000 </V>
            <V ID="137">   0.517484206394210    0.574314430866330    0.000000000000000 </V>
            <V ID="138">   0.560389429140077    0.264123404420924    0.000000000000000 </V>
            <V ID="139">   0.316512438846792    0.456328526531253    0.000000000000000 </V>
            <V ID="140">   0.388585927694506    0.418668141454390    0.000000000000000 </V>
            <V ID="141">   0.301273296819202    0.334183172264509    0.000000000000000 </V>
            <V ID="142">   0.073647065051324    0.614991180222544    0.000000000000000 </V>
            <V ID="143">   0.486694444102571    0.645243152445495    0.000000000000000 </V>
            <V ID="144">   0.072415763310363    0.452516586466864    0.000000000000000 </V>
            <V ID="145">   0.299424865460074    0.205965968999778    0.000000000000000 </V>
            <V ID="146">   0.384753408646066    0.567088614242572    0.000000000000000 </V>
            <V ID="147">   0.584711466940796    0.655886359328314    0.000000000000000 </V>
            <V ID="148">   0.581242359168092    0.208340947556592    0.000000000000000 </V>
            <V ID="149">   0.853909025193540    0.335178759456959    0.000000000000000 </V>
            <V ID="150">   0.434267789191287    0.224966200144521    0.000000000000000 </V>
            <V ID="151">   0.661950222122383    0.923979493678692    0.000000000000000 </V>
            <V ID="152">   0.452766153456687    0.528322932258965    0.000000000000000 </V>
            <V ID="153">   0.791069489303429    0.212364500832733    0.000000000000000 </V>
            <V ID="154">   0.696449278848572    0.821469836563270    0.000000000000000 </V>
            <V ID="155">   0.321134096450763    0.152084929063834    0.000000000000000 </V>
            <V ID="156">   0.912141556488386    0.715590249883365    0.000000000000000 </V>
            <V ID="157">   0.729201181583284    0.157268128737590    0.000000000000000 </V>
            <V ID="158">   0.306946621102903    0.078427846273637    0.000000000000000 </V>
            <V ID="159">   0.135952122701972    0.190384783863531    0.000000000000000 </V>
            <V ID="160">   0.136816973879119    0.064468047645113    0.000000000000000 </V>
            <V ID="161">   0.939686619669800    0.175166192178365    0.000000000000000 </V>
            <V ID="162">   0.381779953471257    0.120604517092381    0.000000000000000 </V>
            <V ID="163">   0.797042095003046    0.116159357391572    0.000000000000000 </V>
            <V ID="164">   0.734564458565311    0.731191150793400    0.000000000000000 </V>
            <V ID="165">   0.339602427377767    0.930349910942219    0.000000000000000 </V>
            <V ID="166">   0.738293175453766    0.278427379598609    0.000000000000000 </V>
            <V ID="167">   0.284333030643303    0.836805380999455    0.000000000000000 </V>
            <V ID="168">   0.928290171030037    0.283647808312072    0.000000000000000 </V>
            <V ID="169">   0.380602928428175    0.849156717219487    0.000000000000000 </V>
            <V ID="170">   0.288320588763679    0.755648807758260    0.000000000000000 </V>
            <V ID="171">   0.050204897534523    0.942030335370660    0.000000000000000 </V>
            <V ID="172">   0.933937241648953    0.077221880027174    0.000000000000000 </V>
            <V ID="173">   0.846192447377564    0.843032963792302    0.000000000000000 </V>
            <V ID="174">   0.850101714532064    0.775887947570589    0.000000000000000 </V>
            <V ID="175">   0.086632853665057    0.822556071079072    0.000000000000000 </V>
            <V ID="176">   0.609118595064107    0.302149421815376    0.000000000000000 </V>
            <V ID="177">   0.079018715108461    0.528296479242156    0.000000000000000 </V>
            <V ID="178">   0.217944662455156    0.069576727068050    0.000000000000000 </V>
            <V ID="179">   0.939647167391698    0.442417010601074    0.000000000000000 </V>
            <V ID="180">   0.062862295835208    0.194736724789826    0.000000000000000 </V>
            <V ID="181">   0.781622436353273    0.560307478624669    0.000000000000000 </V>
            <V ID="182">   0.654657784088926    0.519929940805294    0.000000000000000 </V>
            <V ID="183">   0.796167364622505    0.051280740921623    0.000000000000000 </V>
            <V ID="184">   0.142315355394550    0.485116798944985    0.000000000000000 </V>
            <V ID="185">   0.146452045812875    0.788605571456092    0.000000000000000 </V>
            <V ID="186">   0.068481206785061    0.388257270094159    0.000000000000000 </V>
            <V ID="187">   0.067745191841304    0.687176398166340    0.000000000000000 </V>
            <V ID="188">   0.061564941401417    0.054970090017460    0.000000000000000 </V>
            <V ID="189">   0.940514954910236    0.637439045643252    0.000000000000000 </V>
            <V ID="190">   0.941448490760776    0.946079555369936    0.000000000000000 </V>
            <V ID="191">   0.548578294721079    0.061649664049430    0.000000000000000 </V>
        </VERTEX>
        <EDGE>
            <E ID="0">      0       4 </E>
            <E ID="1">      4       5 </E>
            <E ID="2">      5       6 </E>
            <E ID="3">      6       7 </E>
            <E ID="4">      7       8 </E>
            <E ID="5">      8       9 </E>
            <E ID="6">      9      10 </E>
            <E ID="7">     10      11 </E>
            <E ID="8">     11      12 </E>
            <E ID="9">     12      13 </E>
            <E ID="10">     13      14 </E>
            <E ID="11">     14       1 </E>
            <E ID="12">      1      15 </E>
            <E ID="13">     15      16 </E>
            <E ID="14">     16      17 </E>
            <E ID="15">     17      18 </E>
            <E ID="16">     18      19 </E>
            <E ID="17">     19      20 </E>
            <E ID="18">     20      21 </E>
            <E ID="19">     21      22 </E>
            <E ID="20">     22      23 </E>
            <E ID="21">     23      24 </E>
            <E ID="22">     24      25 </E>
            <E ID="23">     25       2 </E>
            <E ID="24">      2      26 </E>
            <E ID="25">     26      27 </E>
            <E ID="26">     27      28 </E>
            <E ID="27">     28      29 </E>
            <E ID="28">     29      30 </E>
            <E ID="29">     30      31 </E>
            <E ID="30">     31      32 </E>
            <E ID="31">     32      33 </E>
            <E ID="32">     33      34 </E>
            <E ID="33">     34      35 </E>
            <E ID="34">     35      36 </E>
            <E ID="35">     36       3 </E>
            <E ID="36">      3      37 </E>
            <E ID="37">     37      38 </E>
            <E ID="38">     38      39 </E>
            <E ID="39">     39      40 </E>
            <E ID="40">     40      41 </E>
            <E ID="41">     41      42 </E>
            <E ID="42">     42      43 </E>
            <E ID="43">     43      44 </E>
            <E ID="44">     44      45 </E>
            <E ID="45">     45      46 </E>
            <E ID="46">     46      47 </E>
            <E ID="47">     47       0 </E>
            <E ID="48">     35      90 </E>
            <E ID="49">     90      34 </E>
            <E ID="50">     87      24 </E>
            <E ID="51">     25      87 </E>
            <E ID="52">     89      46 </E>
            <E ID="53">     47      89 </E>
            <E ID="54">     88      13 </E>
            <E ID="55">     14      88 </E>
            <E ID="56">     80      34 </E>
            <E ID="57">     90      80 </E>
            <E ID="58">     38      61 </E>
            <E ID="59">     61      37 </E>
            <E ID="60">     56      80 </E>
            <E ID="61">     90      56 </E>
            <E ID="62">     90      60 </E>
            <E ID="63">     60      56 </E>
            <E ID="64">      8      85 </E>
            <E ID="65">     85       7 </E>
            <E ID="66">     36      90 </E>
            <E ID="67">     36      60 </E>
            <E ID="68">     93      91 </E>
            <E ID="69">     91      65 </E>
            <E ID="70">     65      93 </E>
            <E ID="71">     83      50 </E>
            <E ID="72">     50     102 </E>
            <E ID="73">    102      83 </E>
            <E ID="74">     79      98 </E>
            <E ID="75">     98     102 </E>
            <E ID="76">    102      79 </E>
            <E ID="77">    103      94 </E>
            <E ID="78">     94      72 </E>
            <E ID="79">     72     103 </E>
            <E ID="80">     72      92 </E>
            <E ID="81">     92     103 </E>
            <E ID="82">     21     105 </E>
            <E ID="83">    105      20 </E>
            <E ID="84">    105      91 </E>
            <E ID="85">     91      20 </E>
            <E ID="86">     94     107 </E>
            <E ID="87">    107      72 </E>
            <E ID="88">     52      94 </E>
            <E ID="89">     94     108 </E>
            <E ID="90">    108      52 </E>
            <E ID="91">     76     100 </E>
            <E ID="92">    100     110 </E>
            <E ID="93">    110      76 </E>
            <E ID="94">    110      99 </E>
            <E ID="95">     99      76 </E>
            <E ID="96">    111      95 </E>
            <E ID="97">     95      67 </E>
            <E ID="98">     67     111 </E>
            <E ID="99">     79     109 </E>
            <E ID="100">    109     112 </E>
            <E ID="101">    112      79 </E>
            <E ID="102">    112      96 </E>
            <E ID="103">     96      79 </E>
            <E ID="104">     77     104 </E>
            <E ID="105">    104     113 </E>
            <E ID="106">    113      77 </E>
            <E ID="107">     91     114 </E>
            <E ID="108">    114      65 </E>
            <E ID="109">    115     101 </E>
            <E ID="110">    101      64 </E>
            <E ID="111">     64     115 </E>
            <E ID="112">    117     104 </E>
            <E ID="113">     77     117 </E>
            <E ID="114">    118      50 </E>
            <E ID="115">     83     118 </E>
            <E ID="116">     52     101 </E>
            <E ID="117">    101     119 </E>
            <E ID="118">    119      52 </E>
            <E ID="119">     65     106 </E>
            <E ID="120">    106     120 </E>
            <E ID="121">    120      65 </E>
            <E ID="122">    120      93 </E>
            <E ID="123">    122     100 </E>
            <E ID="124">     76     122 </E>
            <E ID="125">    123     116 </E>
            <E ID="126">    116      78 </E>
            <E ID="127">     78     123 </E>
            <E ID="128">     66      97 </E>
            <E ID="129">     97     124 </E>
            <E ID="130">    124      66 </E>
            <E ID="131">     69     115 </E>
            <E ID="132">    115     124 </E>
            <E ID="133">    124      69 </E>
            <E ID="134">    126     101 </E>
            <E ID="135">     52     126 </E>
            <E ID="136">    108     126 </E>
            <E ID="137">    127     104 </E>
            <E ID="138">    104      71 </E>
            <E ID="139">     71     127 </E>
            <E ID="140">    127     111 </E>
            <E ID="141">     67     127 </E>
            <E ID="142">     58      54 </E>
            <E ID="143">     54     128 </E>
            <E ID="144">    128      58 </E>
            <E ID="145">     77     118 </E>
            <E ID="146">    118     129 </E>
            <E ID="147">    129      77 </E>
            <E ID="148">    129     106 </E>
            <E ID="149">    106      77 </E>
            <E ID="150">    132     115 </E>
            <E ID="151">     64     132 </E>
            <E ID="152">    132     125 </E>
            <E ID="153">    125      66 </E>
            <E ID="154">     66     132 </E>
            <E ID="155">    133     128 </E>
            <E ID="156">    128      82 </E>
            <E ID="157">     82     133 </E>
            <E ID="158">     82     100 </E>
            <E ID="159">    100     133 </E>
            <E ID="160">    119     134 </E>
            <E ID="161">    134      52 </E>
            <E ID="162">    104     136 </E>
            <E ID="163">    136      71 </E>
            <E ID="164">    137     136 </E>
            <E ID="165">    136      48 </E>
            <E ID="166">     48     137 </E>
            <E ID="167">    138     113 </E>
            <E ID="168">    113      67 </E>
            <E ID="169">     67     138 </E>
            <E ID="170">     67     109 </E>
            <E ID="171">    109     138 </E>
            <E ID="172">    139     121 </E>
            <E ID="173">    121      70 </E>
            <E ID="174">     70     139 </E>
            <E ID="175">     70      99 </E>
            <E ID="176">     99     139 </E>
            <E ID="177">     49     111 </E>
            <E ID="178">    111     140 </E>
            <E ID="179">    140      49 </E>
            <E ID="180">     71     121 </E>
            <E ID="181">    121     140 </E>
            <E ID="182">    140      71 </E>
            <E ID="183">    141     100 </E>
            <E ID="184">     82     141 </E>
            <E ID="185">     82      95 </E>
            <E ID="186">     95     141 </E>
            <E ID="187">    101     143 </E>
            <E ID="188">    143      64 </E>
            <E ID="189">    145      95 </E>
            <E ID="190">     82     145 </E>
            <E ID="191">     63      95 </E>
            <E ID="192">    145      63 </E>
            <E ID="193">    121     146 </E>
            <E ID="194">    146      70 </E>
            <E ID="195">    146     108 </E>
            <E ID="196">    108      70 </E>
            <E ID="197">    148     102 </E>
            <E ID="198">     50     148 </E>
            <E ID="199">    148     109 </E>
            <E ID="200">     79     148 </E>
            <E ID="201">     62      55 </E>
            <E ID="202">     55     149 </E>
            <E ID="203">    149      62 </E>
            <E ID="204">     84      93 </E>
            <E ID="205">     93     149 </E>
            <E ID="206">    149      84 </E>
            <E ID="207">    150      95 </E>
            <E ID="208">     63     150 </E>
            <E ID="209">    150     109 </E>
            <E ID="210">     67     150 </E>
            <E ID="211">    151      97 </E>
            <E ID="212">     66     151 </E>
            <E ID="213">    136     152 </E>
            <E ID="214">    152      71 </E>
            <E ID="215">    152     121 </E>
            <E ID="216">     62     153 </E>
            <E ID="217">    153      55 </E>
            <E ID="218">    154     151 </E>
            <E ID="219">     66     154 </E>
            <E ID="220">     53     151 </E>
            <E ID="221">    154      53 </E>
            <E ID="222">    145     155 </E>
            <E ID="223">    155      63 </E>
            <E ID="224">    145      54 </E>
            <E ID="225">     54     155 </E>
            <E ID="226">    156     123 </E>
            <E ID="227">     78     156 </E>
            <E ID="228">    157      98 </E>
            <E ID="229">     98      75 </E>
            <E ID="230">     75     157 </E>
            <E ID="231">    158     155 </E>
            <E ID="232">     54     158 </E>
            <E ID="233">    159      89 </E>
            <E ID="234">     89      58 </E>
            <E ID="235">     58     159 </E>
            <E ID="236">    128     159 </E>
            <E ID="237">     85      96 </E>
            <E ID="238">     96     162 </E>
            <E ID="239">    162      85 </E>
            <E ID="240">    155     162 </E>
            <E ID="241">    162      63 </E>
            <E ID="242">    163      88 </E>
            <E ID="243">     88      59 </E>
            <E ID="244">     59     163 </E>
            <E ID="245">     51     116 </E>
            <E ID="246">    116     164 </E>
            <E ID="247">    164      51 </E>
            <E ID="248">     34     165 </E>
            <E ID="249">    165      33 </E>
            <E ID="250">     80     165 </E>
            <E ID="251">     83     153 </E>
            <E ID="252">    153     166 </E>
            <E ID="253">    166      83 </E>
            <E ID="254">    166     118 </E>
            <E ID="255">     62     166 </E>
            <E ID="256">    149     168 </E>
            <E ID="257">    168      84 </E>
            <E ID="258">     55     168 </E>
            <E ID="259">    169     119 </E>
            <E ID="260">    119      69 </E>
            <E ID="261">     69     169 </E>
            <E ID="262">     69     135 </E>
            <E ID="263">    135     169 </E>
            <E ID="264">    170      94 </E>
            <E ID="265">     52     170 </E>
            <E ID="266">    134     170 </E>
            <E ID="267">    171       3 </E>
            <E ID="268">     37     171 </E>
            <E ID="269">    171      36 </E>
            <E ID="270">     61     171 </E>
            <E ID="271">    172       1 </E>
            <E ID="272">     15     172 </E>
            <E ID="273">    172      14 </E>
            <E ID="274">     57      53 </E>
            <E ID="275">     53     173 </E>
            <E ID="276">    173      57 </E>
            <E ID="277">     53      86 </E>
            <E ID="278">     86     173 </E>
            <E ID="279">     86     123 </E>
            <E ID="280">    123     174 </E>
            <E ID="281">    174      86 </E>
            <E ID="282">    176     118 </E>
            <E ID="283">     77     176 </E>
            <E ID="284">    113     176 </E>
            <E ID="285">    176      50 </E>
            <E ID="286">    145     128 </E>
            <E ID="287">    171      60 </E>
            <E ID="288">     61      60 </E>
            <E ID="289">    105      78 </E>
            <E ID="290">     78     114 </E>
            <E ID="291">    114     105 </E>
            <E ID="292">     70     103 </E>
            <E ID="293">    103      99 </E>
            <E ID="294">     92      99 </E>
            <E ID="295">    120      62 </E>
            <E ID="296">    149     120 </E>
            <E ID="297">    170     107 </E>
            <E ID="298">    108     103 </E>
            <E ID="299">     49     141 </E>
            <E ID="300">    141     111 </E>
            <E ID="301">    112      63 </E>
            <E ID="302">    162     112 </E>
            <E ID="303">    157      83 </E>
            <E ID="304">    102     157 </E>
            <E ID="305">    110      49 </E>
            <E ID="306">     49     139 </E>
            <E ID="307">    139     110 </E>
            <E ID="308">    110     141 </E>
            <E ID="309">    122      74 </E>
            <E ID="310">     74     133 </E>
            <E ID="311">    133     122 </E>
            <E ID="312">    126      68 </E>
            <E ID="313">     68     143 </E>
            <E ID="314">    143     126 </E>
            <E ID="315">    119     115 </E>
            <E ID="316">    116     114 </E>
            <E ID="317">    117      48 </E>
            <E ID="318">    136     117 </E>
            <E ID="319">    113     127 </E>
            <E ID="320">    106     117 </E>
            <E ID="321">    129      62 </E>
            <E ID="322">    120     129 </E>
            <E ID="323">    146      68 </E>
            <E ID="324">    126     146 </E>
            <E ID="325">     50     138 </E>
            <E ID="326">    138     148 </E>
            <E ID="327">    112     150 </E>
            <E ID="328">    140     127 </E>
            <E ID="329">    176     138 </E>
            <E ID="330">    124     132 </E>
            <E ID="331">     86     164 </E>
            <E ID="332">    164     123 </E>
            <E ID="333">    129     166 </E>
            <E ID="334">    169     134 </E>
            <E ID="335">    140     139 </E>
            <E ID="336">    152      68 </E>
            <E ID="337">    146     152 </E>
            <E ID="338">    156      73 </E>
            <E ID="339">     73     174 </E>
            <E ID="340">    174     156 </E>
            <E ID="341">    125      51 </E>
            <E ID="342">    164     125 </E>
            <E ID="343">     74     159 </E>
            <E ID="344">    159     133 </E>
            <E ID="345">     68     137 </E>
            <E ID="346">    137     143 </E>
            <E ID="347">     75     163 </E>
            <E ID="348">    163     157 </E>
            <E ID="349">    167     170 </E>
            <E ID="350">    134     167 </E>
            <E ID="351">    152     137 </E>
            <E ID="352">    158      85 </E>
            <E ID="353">    162     158 </E>
            <E ID="354">    174     173 </E>
            <E ID="355">     31      97 </E>
            <E ID="356">     97      30 </E>
            <E ID="357">    151      30 </E>
            <E ID="358">      9      96 </E>
            <E ID="359">     96       8 </E>
            <E ID="360">     19      84 </E>
            <E ID="361">     84      18 </E>
            <E ID="362">      7     158 </E>
            <E ID="363">    158       6 </E>
            <E ID="364">     87      73 </E>
            <E ID="365">     73      24 </E>
            <E ID="366">    172      59 </E>
            <E ID="367">     88     172 </E>
            <E ID="368">     61     175 </E>
            <E ID="369">    175      60 </E>
            <E ID="370">    175      56 </E>
            <E ID="371">     38     175 </E>
            <E ID="372">    142      40 </E>
            <E ID="373">     41     142 </E>
            <E ID="374">    142      92 </E>
            <E ID="375">     72     142 </E>
            <E ID="376">      5     160 </E>
            <E ID="377">    160       4 </E>
            <E ID="378">     89     160 </E>
            <E ID="379">    160      58 </E>
            <E ID="380">     16     161 </E>
            <E ID="381">    161      15 </E>
            <E ID="382">    161     172 </E>
            <E ID="383">    161      59 </E>
            <E ID="384">     43     144 </E>
            <E ID="385">    144      42 </E>
            <E ID="386">     32     135 </E>
            <E ID="387">    135      31 </E>
            <E ID="388">    135      97 </E>
            <E ID="389">    124     135 </E>
            <E ID="390">    107     130 </E>
            <E ID="391">    130      72 </E>
            <E ID="392">    151      29 </E>
            <E ID="393">    165      32 </E>
            <E ID="394">    165     135 </E>
            <E ID="395">    165     169 </E>
            <E ID="396">     59      55 </E>
            <E ID="397">    153      59 </E>
            <E ID="398">    153     163 </E>
            <E ID="399">    157     153 </E>
            <E ID="400">     17     161 </E>
            <E ID="401">    161      55 </E>
            <E ID="402">    161     168 </E>
            <E ID="403">     17     168 </E>
            <E ID="404">     65     131 </E>
            <E ID="405">    131     106 </E>
            <E ID="406">     48      81 </E>
            <E ID="407">     81     147 </E>
            <E ID="408">    147      48 </E>
            <E ID="409">    147     137 </E>
            <E ID="410">    143     147 </E>
            <E ID="411">    147      64 </E>
            <E ID="412">     51      81 </E>
            <E ID="413">     81     131 </E>
            <E ID="414">    131      51 </E>
            <E ID="415">    131     116 </E>
            <E ID="416">     51     147 </E>
            <E ID="417">    125     147 </E>
            <E ID="418">    147     132 </E>
            <E ID="419">    125     154 </E>
            <E ID="420">    154      86 </E>
            <E ID="421">    154     164 </E>
            <E ID="422">     18     168 </E>
            <E ID="423">    177      42 </E>
            <E ID="424">    144     177 </E>
            <E ID="425">    177      92 </E>
            <E ID="426">    142     177 </E>
            <E ID="427">     54     178 </E>
            <E ID="428">    178     158 </E>
            <E ID="429">    178       6 </E>
            <E ID="430">     20     179 </E>
            <E ID="431">    179      19 </E>
            <E ID="432">     91     179 </E>
            <E ID="433">     89     180 </E>
            <E ID="434">    180      46 </E>
            <E ID="435">    159     180 </E>
            <E ID="436">    181      65 </E>
            <E ID="437">    114     181 </E>
            <E ID="438">    181     116 </E>
            <E ID="439">    131     181 </E>
            <E ID="440">    182      48 </E>
            <E ID="441">    117     182 </E>
            <E ID="442">    182     106 </E>
            <E ID="443">    131     182 </E>
            <E ID="444">    183     163 </E>
            <E ID="445">     75     183 </E>
            <E ID="446">     99     184 </E>
            <E ID="447">    184      76 </E>
            <E ID="448">     92     184 </E>
            <E ID="449">    107      56 </E>
            <E ID="450">     56     185 </E>
            <E ID="451">    185     107 </E>
            <E ID="452">    175     130 </E>
            <E ID="453">    130     185 </E>
            <E ID="454">    185     175 </E>
            <E ID="455">    183      13 </E>
            <E ID="456">     88     183 </E>
            <E ID="457">    182      81 </E>
            <E ID="458">    178       5 </E>
            <E ID="459">    178     160 </E>
            <E ID="460">     58     178 </E>
            <E ID="461">    183      12 </E>
            <E ID="462">     75      12 </E>
            <E ID="463">     74     180 </E>
            <E ID="464">    180      45 </E>
            <E ID="465">     74      45 </E>
            <E ID="466">    179      84 </E>
            <E ID="467">     93     179 </E>
            <E ID="468">    177      41 </E>
            <E ID="469">    156      23 </E>
            <E ID="470">     23      73 </E>
            <E ID="471">     56     167 </E>
            <E ID="472">    167      80 </E>
            <E ID="473">    107     167 </E>
            <E ID="474">    177     184 </E>
            <E ID="475">    144     184 </E>
            <E ID="476">    144      76 </E>
            <E ID="477">    167     165 </E>
            <E ID="478">    169     167 </E>
            <E ID="479">    173      87 </E>
            <E ID="480">     87      57 </E>
            <E ID="481">    173      73 </E>
            <E ID="482">    160     188 </E>
            <E ID="483">    188       4 </E>
            <E ID="484">     89     188 </E>
            <E ID="485">     40     187 </E>
            <E ID="486">    187      39 </E>
            <E ID="487">    186      43 </E>
            <E ID="488">     44     186 </E>
            <E ID="489">    186     144 </E>
            <E ID="490">     98      11 </E>
            <E ID="491">     11      75 </E>
            <E ID="492">     39     175 </E>
            <E ID="493">     39     130 </E>
            <E ID="494">    187     130 </E>
            <E ID="495">     76     186 </E>
            <E ID="496">    186     122 </E>
            <E ID="497">    122      44 </E>
            <E ID="498">     44      74 </E>
            <E ID="499">      0     188 </E>
            <E ID="500">    188      47 </E>
            <E ID="501">    187      72 </E>
            <E ID="502">    187     142 </E>
            <E ID="503">     57      26 </E>
            <E ID="504">     27      57 </E>
            <E ID="505">    156      22 </E>
            <E ID="506">    156     189 </E>
            <E ID="507">    189      22 </E>
            <E ID="508">    105     189 </E>
            <E ID="509">    189      78 </E>
            <E ID="510">    190       2 </E>
            <E ID="511">     26     190 </E>
            <E ID="512">    190      87 </E>
            <E ID="513">     25     190 </E>
            <E ID="514">     57     190 </E>
            <E ID="515">    189      21 </E>
            <E ID="516">     98      10 </E>
            <E ID="517">     98     191 </E>
            <E ID="518">    191      10 </E>
            <E ID="519">     96     191 </E>
            <E ID="520">    191      79 </E>
            <E ID="521">    191       9 </E>
            <E ID="522">     53      28 </E>
            <E ID="523">     28     151 </E>
            <E ID="524">     27      53 </E>
        </EDGE>
        <ELEMENT>
            <T ID="0">     33      48      49 </T>
            <T ID="1">     50      22      51 </T>
            <T ID="2">     52      46      53 </T>
            <T ID="3">     54      10      55 </T>
            <T ID="4">     56      49      57 </T>
            <T ID="5">     37      58      59 </T>
            <T ID="6">     60      57      61 </T>
            <T ID="7">     62      63      61 </T>
            <T ID="8">      4      64      65 </T>
            <T ID="9">     48      34      66 </T>
            <T ID="10">     66      67      62 </T>
            <T ID="11">     68      69      70 </T>
            <T ID="12">     71      72      73 </T>
            <T ID="13">     74      75      76 </T>
            <T ID="14">     77      78      79 </T>
            <T ID="15">     80      81      79 </T>
            <T ID="16">     18      82      83 </T>
            <T ID="17">     84      85      83 </T>
            <T ID="18">     78      86      87 </T>
            <T ID="19">     88      89      90 </T>
            <T ID="20">     91      92      93 </T>
            <T ID="21">     94      95      93 </T>
            <T ID="22">     96      97      98 </T>
            <T ID="23">     99     100     101 </T>
            <T ID="24">    102     103     101 </T>
            <T ID="25">    104     105     106 </T>
            <T ID="26">     69     107     108 </T>
            <T ID="27">    109     110     111 </T>
            <T ID="28">    112     104     113 </T>
            <T ID="29">    114      71     115 </T>
            <T ID="30">    116     117     118 </T>
            <T ID="31">    119     120     121 </T>
            <T ID="32">    122      70     121 </T>
            <T ID="33">    123      91     124 </T>
            <T ID="34">    125     126     127 </T>
            <T ID="35">    128     129     130 </T>
            <T ID="36">    131     132     133 </T>
            <T ID="37">    134     116     135 </T>
            <T ID="38">     90     136     135 </T>
            <T ID="39">    137     138     139 </T>
            <T ID="40">    140      98     141 </T>
            <T ID="41">    142     143     144 </T>
            <T ID="42">    145     146     147 </T>
            <T ID="43">    148     149     147 </T>
            <T ID="44">    150     111     151 </T>
            <T ID="45">    152     153     154 </T>
            <T ID="46">    155     156     157 </T>
            <T ID="47">    158     159     157 </T>
            <T ID="48">    118     160     161 </T>
            <T ID="49">    138     162     163 </T>
            <T ID="50">    164     165     166 </T>
            <T ID="51">    167     168     169 </T>
            <T ID="52">    170     171     169 </T>
            <T ID="53">    172     173     174 </T>
            <T ID="54">    175     176     174 </T>
            <T ID="55">    177     178     179 </T>
            <T ID="56">    180     181     182 </T>
            <T ID="57">    183     158     184 </T>
            <T ID="58">    185     186     184 </T>
            <T ID="59">    110     187     188 </T>
            <T ID="60">    189     185     190 </T>
            <T ID="61">    191     189     192 </T>
            <T ID="62">    173     193     194 </T>
            <T ID="63">    195     196     194 </T>
            <T ID="64">    197      72     198 </T>
            <T ID="65">    199      99     200 </T>
            <T ID="66">     76     197     200 </T>
            <T ID="67">    201     202     203 </T>
            <T ID="68">    204     205     206 </T>
            <T ID="69">    207     191     208 </T>
            <T ID="70">    209     170     210 </T>
            <T ID="71">     97     207     210 </T>
            <T ID="72">    211     128     212 </T>
            <T ID="73">    163     213     214 </T>
            <T ID="74">    215     180     214 </T>
            <T ID="75">    201     216     217 </T>
            <T ID="76">    218     212     219 </T>
            <T ID="77">    220     218     221 </T>
            <T ID="78">    192     222     223 </T>
            <T ID="79">    222     224     225 </T>
            <T ID="80">    226     127     227 </T>
            <T ID="81">    228     229     230 </T>
            <T ID="82">    231     225     232 </T>
            <T ID="83">    233     234     235 </T>
            <T ID="84">    144     236     235 </T>
            <T ID="85">    237     238     239 </T>
            <T ID="86">    223     240     241 </T>
            <T ID="87">    242     243     244 </T>
            <T ID="88">    245     246     247 </T>
            <T ID="89">     32     248     249 </T>
            <T ID="90">    248      56     250 </T>
            <T ID="91">    251     252     253 </T>
            <T ID="92">    254     115     253 </T>
            <T ID="93">    252     216     255 </T>
            <T ID="94">    206     256     257 </T>
            <T ID="95">    256     202     258 </T>
            <T ID="96">    259     260     261 </T>
            <T ID="97">    262     263     261 </T>
            <T ID="98">    264      88     265 </T>
            <T ID="99">    161     266     265 </T>
            <T ID="100">    267      36     268 </T>
            <T ID="101">     35     267     269 </T>
            <T ID="102">     59     270     268 </T>
            <T ID="103">    271      12     272 </T>
            <T ID="104">     11     271     273 </T>
            <T ID="105">    274     275     276 </T>
            <T ID="106">    275     277     278 </T>
            <T ID="107">    279     280     281 </T>
            <T ID="108">    282     145     283 </T>
            <T ID="109">    106     284     283 </T>
            <T ID="110">    114     282     285 </T>
            <T ID="111">    143     224     286 </T>
            <T ID="112">    286     190     156 </T>
            <T ID="113">     67     269     287 </T>
            <T ID="114">    287     270     288 </T>
            <T ID="115">    289     290     291 </T>
            <T ID="116">    291     107      84 </T>
            <T ID="117">    175     292     293 </T>
            <T ID="118">    293      81     294 </T>
            <T ID="119">    295     203     296 </T>
            <T ID="120">    296     205     122 </T>
            <T ID="121">    264     297      86 </T>
            <T ID="122">    292     196     298 </T>
            <T ID="123">    298      89      77 </T>
            <T ID="124">    177     299     300 </T>
            <T ID="125">    300     186      96 </T>
            <T ID="126">    301     241     302 </T>
            <T ID="127">    302     238     102 </T>
            <T ID="128">    303      73     304 </T>
            <T ID="129">    228     304      75 </T>
            <T ID="130">    305     306     307 </T>
            <T ID="131">    307     176      94 </T>
            <T ID="132">    299     305     308 </T>
            <T ID="133">    183     308      92 </T>
            <T ID="134">    309     310     311 </T>
            <T ID="135">    311     159     123 </T>
            <T ID="136">    312     313     314 </T>
            <T ID="137">    314     187     134 </T>
            <T ID="138">    131     260     315 </T>
            <T ID="139">    315     117     109 </T>
            <T ID="140">    290     126     316 </T>
            <T ID="141">    317     165     318 </T>
            <T ID="142">    318     162     112 </T>
            <T ID="143">    141     168     319 </T>
            <T ID="144">    137     319     105 </T>
            <T ID="145">    113     149     320 </T>
            <T ID="146">    321     295     322 </T>
            <T ID="147">    148     322     120 </T>
            <T ID="148">    323     312     324 </T>
            <T ID="149">    195     324     136 </T>
            <T ID="150">    198     325     326 </T>
            <T ID="151">    199     326     171 </T>
            <T ID="152">    208     301     327 </T>
            <T ID="153">    209     327     100 </T>
            <T ID="154">    139     182     328 </T>
            <T ID="155">    328     178     140 </T>
            <T ID="156">    325     285     329 </T>
            <T ID="157">    329     284     167 </T>
            <T ID="158">    154     130     330 </T>
            <T ID="159">    150     330     132 </T>
            <T ID="160">    279     331     332 </T>
            <T ID="161">    332     246     125 </T>
            <T ID="162">    255     321     333 </T>
            <T ID="163">    254     333     146 </T>
            <T ID="164">    259     334     160 </T>
            <T ID="165">    306     179     335 </T>
            <T ID="166">    335     181     172 </T>
            <T ID="167">    336     323     337 </T>
            <T ID="168">    215     337     193 </T>
            <T ID="169">    338     339     340 </T>
            <T ID="170">    340     280     226 </T>
            <T ID="171">    341     247     342 </T>
            <T ID="172">    310     343     344 </T>
            <T ID="173">    344     236     155 </T>
            <T ID="174">    313     345     346 </T>
            <T ID="175">    230     347     348 </T>
            <T ID="176">    349     266     350 </T>
            <T ID="177">    345     336     351 </T>
            <T ID="178">    351     213     164 </T>
            <T ID="179">    352     239     353 </T>
            <T ID="180">    353     240     231 </T>
            <T ID="181">    278     281     354 </T>
            <T ID="182">    355     356      29 </T>
            <T ID="183">    211     357     356 </T>
            <T ID="184">    358     359       5 </T>
            <T ID="185">    359     237      64 </T>
            <T ID="186">     16     360     361 </T>
            <T ID="187">      3     362     363 </T>
            <T ID="188">     65     352     362 </T>
            <T ID="189">    364     365      50 </T>
            <T ID="190">    366     243     367 </T>
            <T ID="191">     55     273     367 </T>
            <T ID="192">    288     368     369 </T>
            <T ID="193">    370      63     369 </T>
            <T ID="194">    368      58     371 </T>
            <T ID="195">    372      40     373 </T>
            <T ID="196">    374      80     375 </T>
            <T ID="197">      1     376     377 </T>
            <T ID="198">    234     378     379 </T>
            <T ID="199">     13     380     381 </T>
            <T ID="200">    382     272     381 </T>
            <T ID="201">    366     382     383 </T>
            <T ID="202">     42     384     385 </T>
            <T ID="203">     30     386     387 </T>
            <T ID="204">    388     355     387 </T>
            <T ID="205">    262     133     389 </T>
            <T ID="206">    388     389     129 </T>
            <T ID="207">     87     390     391 </T>
            <T ID="208">    392      28     357 </T>
            <T ID="209">     31     249     393 </T>
            <T ID="210">    394     386     393 </T>
            <T ID="211">    395     263     394 </T>
            <T ID="212">    396     217     397 </T>
            <T ID="213">    397     398     244 </T>
            <T ID="214">    399     251     303 </T>
            <T ID="215">    348     398     399 </T>
            <T ID="216">    380      14     400 </T>
            <T ID="217">    396     383     401 </T>
            <T ID="218">    258     401     402 </T>
            <T ID="219">    403     402     400 </T>
            <T ID="220">    404     405     119 </T>
            <T ID="221">    406     407     408 </T>
            <T ID="222">    408     409     166 </T>
            <T ID="223">    410     411     188 </T>
            <T ID="224">    410     346     409 </T>
            <T ID="225">    412     413     414 </T>
            <T ID="226">    414     415     245 </T>
            <T ID="227">    407     412     416 </T>
            <T ID="228">    341     417     416 </T>
            <T ID="229">    151     411     418 </T>
            <T ID="230">    152     418     417 </T>
            <T ID="231">    419     219     153 </T>
            <T ID="232">    277     221     420 </T>
            <T ID="233">    420     421     331 </T>
            <T ID="234">    342     421     419 </T>
            <T ID="235">     15     422     403 </T>
            <T ID="236">    361     257     422 </T>
            <T ID="237">    423     385     424 </T>
            <T ID="238">    425     374     426 </T>
            <T ID="239">    232     427     428 </T>
            <T ID="240">    429     363     428 </T>
            <T ID="241">     17     430     431 </T>
            <T ID="242">    430      85     432 </T>
            <T ID="243">     52     433     434 </T>
            <T ID="244">    433     233     435 </T>
            <T ID="245">    436     108     437 </T>
            <T ID="246">    438     415     439 </T>
            <T ID="247">    404     436     439 </T>
            <T ID="248">    316     438     437 </T>
            <T ID="249">    440     317     441 </T>
            <T ID="250">    442     405     443 </T>
            <T ID="251">    320     442     441 </T>
            <T ID="252">    444     347     445 </T>
            <T ID="253">     95     446     447 </T>
            <T ID="254">    446     294     448 </T>
            <T ID="255">    449     450     451 </T>
            <T ID="256">    452     453     454 </T>
            <T ID="257">    450     370     454 </T>
            <T ID="258">    453     390     451 </T>
            <T ID="259">    455      54     456 </T>
            <T ID="260">    444     456     242 </T>
            <T ID="261">    406     440     457 </T>
            <T ID="262">    457     443     413 </T>
            <T ID="263">      2     429     458 </T>
            <T ID="264">    458     459     376 </T>
            <T ID="265">    427     142     460 </T>
            <T ID="266">    459     460     379 </T>
            <T ID="267">    461       9     455 </T>
            <T ID="268">    462     461     445 </T>
            <T ID="269">    435     343     463 </T>
            <T ID="270">    464      45     434 </T>
            <T ID="271">    465     464     463 </T>
            <T ID="272">    466     360     431 </T>
            <T ID="273">    432      68     467 </T>
            <T ID="274">    204     466     467 </T>
            <T ID="275">    423     468      41 </T>
            <T ID="276">    468     426     373 </T>
            <T ID="277">    469     470     338 </T>
            <T ID="278">     21     365     470 </T>
            <T ID="279">     60     471     472 </T>
            <T ID="280">    473     471     449 </T>
            <T ID="281">    349     473     297 </T>
            <T ID="282">    425     474     448 </T>
            <T ID="283">    474     424     475 </T>
            <T ID="284">    476     447     475 </T>
            <T ID="285">    250     472     477 </T>
            <T ID="286">    478     350     334 </T>
            <T ID="287">    477     478     395 </T>
            <T ID="288">    479     480     276 </T>
            <T ID="289">    364     479     481 </T>
            <T ID="290">    481     354     339 </T>
            <T ID="291">    377     482     483 </T>
            <T ID="292">    482     378     484 </T>
            <T ID="293">     39     485     486 </T>
            <T ID="294">    487      43     488 </T>
            <T ID="295">    384     487     489 </T>
            <T ID="296">    229     490     491 </T>
            <T ID="297">    462     491       8 </T>
            <T ID="298">    492     371      38 </T>
            <T ID="299">    492     493     452 </T>
            <T ID="300">    493     486     494 </T>
            <T ID="301">    124     495     496 </T>
            <T ID="302">    495     476     489 </T>
            <T ID="303">    309     497     498 </T>
            <T ID="304">    465     498      44 </T>
            <T ID="305">    488     497     496 </T>
            <T ID="306">     47     499     500 </T>
            <T ID="307">    484      53     500 </T>
            <T ID="308">    499       0     483 </T>
            <T ID="309">    501     391     494 </T>
            <T ID="310">    375     501     502 </T>
            <T ID="311">    485     372     502 </T>
            <T ID="312">    503      25     504 </T>
            <T ID="313">    505      20     469 </T>
            <T ID="314">    505     506     507 </T>
            <T ID="315">    289     508     509 </T>
            <T ID="316">    506     227     509 </T>
            <T ID="317">    510      24     511 </T>
            <T ID="318">    512      51     513 </T>
            <T ID="319">     23     510     513 </T>
            <T ID="320">    511     503     514 </T>
            <T ID="321">    512     514     480 </T>
            <T ID="322">     19     507     515 </T>
            <T ID="323">    515     508      82 </T>
            <T ID="324">      7     490     516 </T>
            <T ID="325">    516     517     518 </T>
            <T ID="326">    103     519     520 </T>
            <T ID="327">    517      74     520 </T>
            <T ID="328">    518     521       6 </T>
            <T ID="329">    521     519     358 </T>
            <T ID="330">    220     522     523 </T>
            <T ID="331">     27     392     523 </T>
            <T ID="332">    274     504     524 </T>
            <T ID="333">     26     522     524 </T>
        </ELEMENT>
        <COMPOSITE>
            <C ID="0"> T[0-333] </C>
            <C ID="1"> E[0-11] </C>
            <C ID="2"> E[12-23] </C>
            <C ID="3"> E[24-35] </C>
            <C ID="4"> E[36-47] </C>
        </COMPOSITE>
        <DOMAIN> C[0] </DOMAIN>
    </GEOMETRY>
</NEKTAR>
